cotload/Unit.py
cotload/__init__.py
cotload-1.0.0.dist-info/LICENCE
cotload-1.0.0.dist-info/METADATA
cotload-1.0.0.dist-info/WHEEL
cotload-1.0.0.dist-info/top_level.txt
cotload-1.0.0.dist-info/RECORD
