Metadata-Version: 2.1
Name: cotload
Version: 1.0.0
Summary: Cotload CORE
Home-page: https://github.com/pypa/sampleproject
Author: Aryan Thakur
Author-email: aryan.aparna.thakur@gmail.com
License: UNKNOWN
Platform: UNKNOWN
Classifier: Programming Language :: Python :: 3
Classifier: License :: OSI Approved :: MIT License
Classifier: Operating System :: OS Independent
Requires-Python: >=3.7
